drools/__init__.py
drools/dispatch.py
drools/exceptions.py
drools/rule.py
drools/ruleset.py
drools/jars/__init__.py
drools/jars/drools-ansible-rulebook-integration-runtime-1.0.11-SNAPSHOT.jar
drools_jpy-0.3.14.dist-info/licenses/LICENSE
drools_jpy-0.3.14.dist-info/METADATA
drools_jpy-0.3.14.dist-info/WHEEL
drools_jpy-0.3.14.dist-info/top_level.txt
drools_jpy-0.3.14.dist-info/RECORD
