Metadata-Version: 2.4
Name: drools_jpy
Version: 0.3.14
Summary: A Python package to directly call Drools Java classes from python
Author-email: Madhu Kanoor <author@example.com>
License:                                  Apache License
Project-URL: Homepage, https://github.com/ansible/drools_jpy
Project-URL: Bug Tracker, https://github.com/ansible/drools_jpy/issues
Classifier: Programming Language :: Python :: 3
Classifier: License :: OSI Approved :: Apache Software License
Classifier: Operating System :: OS Independent
Classifier: Development Status :: 5 - Production/Stable
Requires-Python: >=3.7
License-File: LICENSE
Requires-Dist: jpy
Provides-Extra: local
Requires-Dist: flake8; extra == "local"
Requires-Dist: black; extra == "local"
Requires-Dist: isort; extra == "local"
Requires-Dist: tox; extra == "local"
Requires-Dist: pyyaml; extra == "local"
Provides-Extra: tests
Requires-Dist: coverage>=5.0.3; extra == "tests"
Requires-Dist: pytest; extra == "tests"
Requires-Dist: pytest-asyncio; extra == "tests"
Requires-Dist: pytest-cov; extra == "tests"
Requires-Dist: tox; extra == "tests"
Provides-Extra: dev
Requires-Dist: drools_jpy[local]; extra == "dev"
Requires-Dist: drools_jpy[tests]; extra == "dev"
Dynamic: license-file
